[
  // SingleChoice
  {
    "Content": "What is the capital of France?",
    "Image": null,
    "Audio": null,
    "QuestionFolder": {
      "Name": "Geography"
    },
    "QuestionType": 1,
    "QuestionLable": {
      "Name": "Capital",
      "Color": "#FF0000"
    },
    "Answers": [
      {
        "Content": "Paris",
        "IsCorrect": true
      },
      {
        "Content": "London",
        "IsCorrect": false
      },
      {
        "Content": "Berlin",
        "IsCorrect": false
      },
      {
        "Content": "Madrid",
        "IsCorrect": false
      }
    ]
  },
  {
    "Content": "What is the largest desert in the world?",
    "Image": null,
    "Audio": null,
    "QuestionFolder": {
      "Name": "Geography"
    },
    "QuestionType": 1,
    "QuestionLable": {
      "Name": "Desert"
    },
    "Answers": [
      {
        "Content": "Sahara",
        "IsCorrect": true
      },
      {
        "Content": "Arctic",
        "IsCorrect": false
      },
      {
        "Content": "Gobi",
        "IsCorrect": false
      },
      {
        "Content": "Antarctic",
        "IsCorrect": false
      }
    ]
  },
  {
    "Content": "Which continent is the largest by land area?",
    "Image": null,
    "Audio": null,
    "QuestionFolder": {
      "Name": "Geography"
    },
    "QuestionType": 1,
    "QuestionLable": {
      "Name": "Continent"
    },
    "Answers": [
      {
        "Content": "Asia",
        "IsCorrect": true
      },
      {
        "Content": "Africa",
        "IsCorrect": false
      },
      {
        "Content": "North America",
        "IsCorrect": false
      },
      {
        "Content": "South America",
        "IsCorrect": false
      }
    ]
  },
  {
    "Content": "What is the world's longest river?",
    "Image": null,
    "Audio": null,
    "QuestionFolder": {
      "Name": "Geography"
    },
    "QuestionType": 1,
    "QuestionLable": {
      "Name": "River"
    },
    "Answers": [
      {
        "Content": "Nile",
        "IsCorrect": true
      },
      {
        "Content": "Amazon",
        "IsCorrect": false
      },
      {
        "Content": "Yangtze",
        "IsCorrect": false
      },
      {
        "Content": "Mississippi",
        "IsCorrect": false
      }
    ]
  },
  {
    "Content": "Which country is known as the 'Land of the Rising Sun'?",
    "Image": null,
    "Audio": null,
    "QuestionFolder": {
      "Name": "Geography"
    },
    "QuestionType": 1,
    "QuestionLable": {
      "Name": "Country Nickname"
    },
    "Answers": [
      {
        "Content": "Japan",
        "IsCorrect": true
      },
      {
        "Content": "China",
        "IsCorrect": false
      },
      {
        "Content": "Korea",
        "IsCorrect": false
      },
      {
        "Content": "Vietnam",
        "IsCorrect": false
      }
    ]
  },
  // MultipleChoice
  {
    "Content": "Who formulated the theory of relativity?",
    "Image": null,
    "Audio": null,
    "QuestionFolder": {
      "Name": "Science"
    },
    "QuestionType": 2,
    "QuestionLable": {
      "Name": "Scientist"
    },
    "Answers": [
      {
        "Content": "Albert Einstein",
        "IsCorrect": true
      },
      {
        "Content": "Isaac Newton",
        "IsCorrect": false
      },
      {
        "Content": "Max Planck",
        "IsCorrect": true
      },
      {
        "Content": "Niels Bohr",
        "IsCorrect": false
      }
    ]
  },
  {
    "Content": "Who is the author of the novel \"War and Peace\"?",
    "Image": null,
    "Audio": null,
    "QuestionFolder": {
      "Name": "Literature"
    },
    "QuestionType": 2,
    "QuestionLable": {
      "Name": "Author"
    },
    "Answers": [
      {
        "Content": "Leo Tolstoy",
        "IsCorrect": true
      },
      {
        "Content": "Fyodor Dostoevsky",
        "IsCorrect": false
      },
      {
        "Content": "Anton Chekhov",
        "IsCorrect": false
      },
      {
        "Content": "Nikolai Gogol",
        "IsCorrect": false
      }
    ]
  },
  {
    "Content": "Who wrote the book \"Pride and Prejudice\"?",
    "Image": null,
    "Audio": null,
    "QuestionFolder": {
      "Name": "Literature"
    },
    "QuestionType": 2,
    "QuestionLable": {
      "Name": "Author"
    },
    "Answers": [
      {
        "Content": "Jane Austen",
        "IsCorrect": true
      },
      {
        "Content": "Charlotte Brontë",
        "IsCorrect": false
      },
      {
        "Content": "Emily Dickinson",
        "IsCorrect": false
      },
      {
        "Content": "Virginia Woolf",
        "IsCorrect": false
      }
    ]
  },
  {
    "Content": "Who proposed the theory of quantum mechanics?",
    "Image": null,
    "Audio": null,
    "QuestionFolder": {
      "Name": "Science"
    },
    "QuestionType": 2,
    "QuestionLable": {
      "Name": "Scientist"
    },
    "Answers": [
      {
        "Content": "Max Planck",
        "IsCorrect": true
      },
      {
        "Content": "Albert Einstein",
        "IsCorrect": false
      },
      {
        "Content": "Niels Bohr",
        "IsCorrect": true
      },
      {
        "Content": "Werner Heisenberg",
        "IsCorrect": false
      }
    ]
  },
  {
    "Content": "Who authored the novel \"1984\"?",
    "Image": null,
    "Audio": null,
    "QuestionFolder": {
      "Name": "Literature"
    },
    "QuestionType": 2,
    "QuestionLable": {
      "Name": "Author"
    },
    "Answers": [
      {
        "Content": "George Orwell",
        "IsCorrect": true
      },
      {
        "Content": "Aldous Huxley",
        "IsCorrect": false
      },
      {
        "Content": "Ray Bradbury",
        "IsCorrect": false
      },
      {
        "Content": "H.G. Wells",
        "IsCorrect": false
      }
    ]
  },
  // FillBlank
  {
    "Content": "The $_fillblank[1] Ocean is the largest ocean on Earth, covering about $_fillblank[2] of the Earth's surface.",
    "Image": null,
    "Audio": null,
    "QuestionFolder": {
      "Name": "Geography"
    },
    "QuestionType": 4,
    "QuestionLable": {
      "Name": "Geography Facts"
    },
    "Answers": [
      {
        "Content": "$_[1]Pacific",
        "IsCorrect": true
      },
      {
        "Content": "$_[2]30%",
        "IsCorrect": true
      }
    ]
  },
  {
    "Content": "The $_fillblank[1] is the largest mammal on Earth, and it is also the largest animal to have ever lived.",
    "Image": null,
    "Audio": null,
    "QuestionFolder": {
      "Name": "Science"
    },
    "QuestionType": 4,
    "QuestionLable": {
      "Name": "Animal"
    },
    "Answers": [
      {
        "Content": "$_[1]blue whale",
        "IsCorrect": true
      }
    ]
  },
  {
    "Content": "The $_fillblank[1] is the largest desert in the world, and it is located in $_fillblank[2].",
    "Image": null,
    "Audio": null,
    "QuestionFolder": {
      "Name": "Geography"
    },
    "QuestionType": 4,
    "QuestionLable": {
      "Name": "Desert"
    },
    "Answers": [
      {
        "Content": "$_[1]Sahara",
        "IsCorrect": true
      },
      {
        "Content": "$_[2]Africa",
        "IsCorrect": true
      }
    ]
  },
  {
    "Content": "The $_fillblank[1] is the largest planet in our solar system, and it is also known as the $_fillblank[2] planet.",
    "Image": null,
    "Audio": null,
    "QuestionFolder": {
      "Name": "Science"
    },
    "QuestionType": 4,
    "QuestionLable": {
      "Name": "Planet"
    },
    "Answers": [
      {
        "Content": "$_[1]Jupiter",
        "IsCorrect": true
      },
      {
        "Content": "$_[2]gas giant",
        "IsCorrect": true
      }
    ]
  },
  // Matching
  {
    "Content": "{ \"Question\": \"Match the countries with their capitals:\", \"ColumnA\": { \"1\": \"France\", \"2\": \"Germany\", \"3\": \"Spain\", \"4\": \"Italy\" }, \"ColumnB\": { \"1\": \"Berlin\", \"2\": \"Paris\", \"3\": \"Rome\", \"4\": \"Madrid\" } }",
    "Image": null,
    "Audio": null,
    "QuestionFolder": {
      "Name": "Geography"
    },
    "QuestionType": 5,
    "QuestionLable": {
      "Name": "Country-Capital Matching"
    },
    "Answers": [
      {
        "Content": "1_2|2_1|4_3|3_4",
        "IsCorrect": true
      }
    ]
  },
  {
    "Content": "{ \"Question\": \"Match the scientists with their discoveries:\", \"ColumnA\": { \"1\": \"Isaac Newton\", \"2\": \"Albert Einstein\", \"3\": \"Marie Curie\", \"4\": \"Charles Darwin\" }, \"ColumnB\": { \"1\": \"Theory of Evolution\", \"2\": \"Theory of Relativity\", \"3\": \"Law of Gravity\", \"4\": \"Radioactivity\" } }",
    "Image": null,
    "Audio": null,
    "QuestionFolder": {
      "Name": "Science"
    },
    "QuestionType": 5,
    "QuestionLable": {
      "Name": "Scientist-Discovery Matching"
    },
    "Answers": [
      {
        "Content": "1_3|2_2|3_4|4_1",
        "IsCorrect": true
      }
    ]
  },
  // Reading
  {
    "Content": "The Industrial Revolution was a period of major industrialization and innovation that occurred in the late 18th and early 19th centuries, starting in Great Britain and later spreading throughout the world. It marked a significant shift from agrarian and handicraft-based economies to ones dominated by industry and machine manufacturing. The key developments of the Industrial Revolution included the invention of the steam engine, the expansion of factories, and the mass production of goods. These changes led to urbanization as people moved from rural areas to cities in search of employment opportunities in factories. While the Industrial Revolution brought about many advancements and improvements in living standards for some, it also led to significant social and environmental challenges, including poor working conditions, pollution, and the widening gap between the rich and the poor.",
    "Image": null,
    "Audio": null,
    "QuestionFolder": {
      "Name": "Science"
    },
    "QuestionType": 6,
    "QuestionLable": {
      "Name": "Reading Comprehension",
      "Color": "#FF0000"
    },
    "QuestionPassages": [
      {
        "Content": "What was the Industrial Revolution?",
        "QuestionType": 7,
        "Answers": [
          {
            "Content": "A period of major industrialization and innovation that occurred in the late 18th and early 19th centuries.",
            "IsCorrect": true
          },
          {
            "Content": "A period of political revolution in Europe.",
            "IsCorrect": false
          },
          {
            "Content": "A period of religious reform in the Middle East.",
            "IsCorrect": false
          },
          {
            "Content": "A period of artistic and cultural revival in Italy.",
            "IsCorrect": false
          }
        ]
      },
      {
        "Content": "What were some key developments of the Industrial Revolution?",
        "QuestionType": 7,
        "Answers": [
          {
            "Content": "Invention of the steam engine, expansion of factories, and mass production of goods.",
            "IsCorrect": true
          },
          {
            "Content": "Discovery of electricity, invention of the telephone, and development of the internet.",
            "IsCorrect": false
          },
          {
            "Content": "Exploration of space, colonization of new lands, and establishment of trade routes.",
            "IsCorrect": false
          },
          {
            "Content": "Invention of the printing press, development of the scientific method, and discovery of penicillin.",
            "IsCorrect": false
          }
        ]
      }
    ]
  },
  // Writing
  {
    "Content": "Write a short essay on the importance of education in society.",
    "Image": null,
    "Audio": null,
    "QuestionFolder": {
      "Name": "Education"
    },
    "QuestionType": 8,
    "QuestionLable": {
      "Name": "Essay"
    }
  }
]